bettertags/__init__.py
bettertags/config.py
bettertags/plugin.py
bettertags-1.1.0.dist-info/LICENSE
bettertags-1.1.0.dist-info/METADATA
bettertags-1.1.0.dist-info/WHEEL
bettertags-1.1.0.dist-info/entry_points.txt
bettertags-1.1.0.dist-info/top_level.txt
bettertags-1.1.0.dist-info/RECORD
