Metadata-Version: 2.1
Name: bettertags
Version: 1.1.0
Summary: mkdocs-material tag plugin with free enhanced versions of some insiders features
Home-page: https://github.com/rzig/bettertags
Author: ryan
Author-email: Ryan Ziegler <ryan@ziegler.lol>
License: Permission is hereby granted, free of charge, to any person obtaining a copy
Project-URL: Homepage, https://github.com/rzig/bettertags
Keywords: mkdocs,insiders,tags,free
Classifier: License :: OSI Approved :: MIT License
Classifier: Programming Language :: Python
Classifier: Programming Language :: Python :: 3
Requires-Python: >=3.8
License-File: LICENSE
Requires-Dist: markdown
Requires-Dist: mkdocs
